{
  "simple": {
    "id": 44695115,
    "lang": "C++",
    "time": "2\u00a0\u5e74\uff0c1\u00a0\u6708",
    "status_display": "Wrong Answer",
    "runtime": "N/A",
    "url": "/submissions/detail/44695115/",
    "is_pending": "Not Pending",
    "title": "\u4e24\u6570\u76f8\u52a0",
    "timestamp": 1580185327,
    "memory": "N/A"
  },
  "full": {
    "id": "44695115",
    "code": "/**\n * Definition for singly-linked list.\n * struct ListNode {\n *     int val;\n *     ListNode *next;\n *     ListNode(int x) : val(x), next(NULL) {}\n * };\n */\nclass Solution {\npublic:\n    ListNode* addTwoNumbers(ListNode* l1, ListNode* l2) {\n        ListNode *ret, *p1 = l1, *p2 = l2;\n        cout << p1->val;\n        return p1;\n    }\n};",
    "runtime": "N/A",
    "memory": "N/A",
    "rawMemory": "N/A",
    "statusDisplay": "Wrong Answer",
    "timestamp": 1580185327,
    "lang": "cpp",
    "passedTestCaseCnt": 5,
    "totalTestCaseCnt": 1568,
    "sourceUrl": "/problems/add-two-numbers/",
    "question": {
      "titleSlug": "add-two-numbers",
      "title": "Add Two Numbers",
      "translatedTitle": "\u4e24\u6570\u76f8\u52a0",
      "questionId": "2",
      "__typename": "QuestionNode"
    },
    "outputDetail": {
      "codeOutput": "[2,4,3]",
      "expectedOutput": "[7,0,8]",
      "input": "[2,4,3]\n[5,6,4]",
      "compileError": "",
      "runtimeError": "",
      "lastTestcase": "[2,4,3]\n[5,6,4]",
      "__typename": "SubmissionOutputNode"
    },
    "__typename": "GeneralSubmissionNode",
    "submissionComment": null
  }
}
